MANIFEST.in
README.md
create_git_tag.py
setup.py
version.py
statisfaction/__init__.py
statisfaction/_constants.py
statisfaction.egg-info/PKG-INFO
statisfaction.egg-info/SOURCES.txt
statisfaction.egg-info/dependency_links.txt
statisfaction.egg-info/not-zip-safe
statisfaction.egg-info/requires.txt
statisfaction.egg-info/top_level.txt
statisfaction/core/__init__.py
statisfaction/core/_observation.py
statisfaction/duration/__init__.py
statisfaction/duration/_peeking.py
statisfaction/duration/_ttest.py
statisfaction/duration/alpha_refs.csv
statisfaction/io/__init__.py
statisfaction/io/_bigquery.py
statisfaction/io/_csv.py
statisfaction/io/_pandas.py
statisfaction/io/_validation.py
statisfaction/io/_vertica.py
statisfaction/multivariate/__init__.py
statisfaction/multivariate/_bonferroni.py
statisfaction/multivariate/_interpretation.py
statisfaction/multivariate/_multinormaltest.py
statisfaction/multivariate/_t2test.py
statisfaction/suite/__init__.py
statisfaction/suite/_clt.py
statisfaction/suite/_diffindiff.py
statisfaction/univariate/__init__.py
statisfaction/univariate/_binomialtest.py
statisfaction/univariate/_bonferroni.py
statisfaction/univariate/_ftest.py
statisfaction/univariate/_interpretation.py
statisfaction/univariate/_normaltest.py
statisfaction/univariate/_ttest.py
statisfaction/univariate/_utest.py
statisfaction/utils/__init__.py
statisfaction/utils/bucket.py
statisfaction/utils/input.py
tests/__init__.py
tests/t_test_confidence_interval.py
tests/test_bonferroni.py
tests/test_bucket.py
tests/test_observation.py
tests/test_peeking.py
tests/test_t_test_power.py