Metadata-Version: 1.0
Name: statisfaction
Version: 0.3.6
Summary: A library to unify statistical testing at BlaBlaCar
Home-page: UNKNOWN
Author: BlaBlaCar Intelligence Team
Author-email: adrien.tordjeman@blablacar.com
License: UNKNOWN
Keywords: statistics hypothesis test testing
Platform: UNKNOWN
